odoo/addons/sale_report_delivered/README.rst
odoo/addons/sale_report_delivered/__init__.py
odoo/addons/sale_report_delivered/__manifest__.py
odoo/addons/sale_report_delivered/i18n/es.po
odoo/addons/sale_report_delivered/i18n/it.po
odoo/addons/sale_report_delivered/i18n/sale_report_delivered.pot
odoo/addons/sale_report_delivered/readme/CONTRIBUTORS.md
odoo/addons/sale_report_delivered/readme/DESCRIPTION.md
odoo/addons/sale_report_delivered/readme/USAGE.md
odoo/addons/sale_report_delivered/reports/__init__.py
odoo/addons/sale_report_delivered/reports/sale_report_delivered.py
odoo/addons/sale_report_delivered/security/ir.model.access.csv
odoo/addons/sale_report_delivered/security/sale_report_security.xml
odoo/addons/sale_report_delivered/static/description/icon.png
odoo/addons/sale_report_delivered/static/description/index.html
odoo/addons/sale_report_delivered/tests/__init__.py
odoo/addons/sale_report_delivered/tests/test_sale_report_delivered.py
odoo/addons/sale_report_delivered/views/sale_report_delivered_views.xml
odoo_addon_sale_report_delivered-18.0.1.0.0.3.dist-info/METADATA
odoo_addon_sale_report_delivered-18.0.1.0.0.3.dist-info/WHEEL
odoo_addon_sale_report_delivered-18.0.1.0.0.3.dist-info/top_level.txt
odoo_addon_sale_report_delivered-18.0.1.0.0.3.dist-info/RECORD
